nevargs/__init__.py
nevargs/dictify.py
nevargs-0.0.5.dist-info/LICENSE.md
nevargs-0.0.5.dist-info/METADATA
nevargs-0.0.5.dist-info/WHEEL
nevargs-0.0.5.dist-info/top_level.txt
nevargs-0.0.5.dist-info/RECORD
