Metadata-Version: 2.1
Name: nevargs
Version: 0.0.5
Summary: Formats strings of args into dicts
Home-page: https://github.com/nevalicjus/nevargs
Author: Nevalicjus
Author-email: nevalicjus@gmail.com
License: UNKNOWN
Project-URL: Author, https://n3v.xyz
Project-URL: Bug Tracker, https://github.com/nevalicjus/nevargs/issues
Platform: UNKNOWN
Classifier: Programming Language :: Python :: 3
Classifier: License :: OSI Approved :: MIT License
Classifier: Operating System :: OS Independent
Requires-Python: >=3.6
License-File: LICENSE.md
